oscontrol/__init__.py
oscontrol/pyarmor_runtime_000000/__init__.py
oscontrol/pyarmor_runtime_000000/pyarmor_runtime.pyd
oscontrol/pyarmor_runtime_000000/__pycache__/__init__.cpython-311.pyc
oscontrol-0.8.dist-info/METADATA
oscontrol-0.8.dist-info/WHEEL
oscontrol-0.8.dist-info/top_level.txt
oscontrol-0.8.dist-info/RECORD
